{
	"configurations" : 
	[
		{
			"abstractTargets" : [],
			"directories" : 
			[
				{
					"build" : ".",
					"jsonFile" : "directory-.-Debug-f6f22219c74102c3da70.json",
					"minimumCMakeVersion" : 
					{
						"string" : "3.15"
					},
					"projectIndex" : 0,
					"source" : ".",
					"targetIndexes" : 
					[
						0,
						1,
						2
					]
				}
			],
			"name" : "Debug",
			"projects" : 
			[
				{
					"directoryIndexes" : 
					[
						0
					],
					"name" : "WordleSolver",
					"targetIndexes" : 
					[
						0,
						1,
						2
					]
				}
			],
			"targets" : 
			[
				{
					"directoryIndex" : 0,
					"id" : "ALL_BUILD::@6890427a1f51a3e7e1df",
					"jsonFile" : "target-ALL_BUILD-Debug-d00ad5da430fcfb9aa1d.json",
					"name" : "ALL_BUILD",
					"projectIndex" : 0
				},
				{
					"directoryIndex" : 0,
					"id" : "WordleSolver::@6890427a1f51a3e7e1df",
					"jsonFile" : "target-WordleSolver-Debug-83e5bff180233c76e19f.json",
					"name" : "WordleSolver",
					"projectIndex" : 0
				},
				{
					"directoryIndex" : 0,
					"id" : "ZERO_CHECK::@6890427a1f51a3e7e1df",
					"jsonFile" : "target-ZERO_CHECK-Debug-7467a3f982a3dc1f794d.json",
					"name" : "ZERO_CHECK",
					"projectIndex" : 0
				}
			]
		},
		{
			"abstractTargets" : [],
			"directories" : 
			[
				{
					"build" : ".",
					"jsonFile" : "directory-.-Release-f6f22219c74102c3da70.json",
					"minimumCMakeVersion" : 
					{
						"string" : "3.15"
					},
					"projectIndex" : 0,
					"source" : ".",
					"targetIndexes" : 
					[
						0,
						1,
						2
					]
				}
			],
			"name" : "Release",
			"projects" : 
			[
				{
					"directoryIndexes" : 
					[
						0
					],
					"name" : "WordleSolver",
					"targetIndexes" : 
					[
						0,
						1,
						2
					]
				}
			],
			"targets" : 
			[
				{
					"directoryIndex" : 0,
					"id" : "ALL_BUILD::@6890427a1f51a3e7e1df",
					"jsonFile" : "target-ALL_BUILD-Release-d00ad5da430fcfb9aa1d.json",
					"name" : "ALL_BUILD",
					"projectIndex" : 0
				},
				{
					"directoryIndex" : 0,
					"id" : "WordleSolver::@6890427a1f51a3e7e1df",
					"jsonFile" : "target-WordleSolver-Release-087731d7c53ea12289e5.json",
					"name" : "WordleSolver",
					"projectIndex" : 0
				},
				{
					"directoryIndex" : 0,
					"id" : "ZERO_CHECK::@6890427a1f51a3e7e1df",
					"jsonFile" : "target-ZERO_CHECK-Release-7467a3f982a3dc1f794d.json",
					"name" : "ZERO_CHECK",
					"projectIndex" : 0
				}
			]
		},
		{
			"abstractTargets" : [],
			"directories" : 
			[
				{
					"build" : ".",
					"jsonFile" : "directory-.-MinSizeRel-f6f22219c74102c3da70.json",
					"minimumCMakeVersion" : 
					{
						"string" : "3.15"
					},
					"projectIndex" : 0,
					"source" : ".",
					"targetIndexes" : 
					[
						0,
						1,
						2
					]
				}
			],
			"name" : "MinSizeRel",
			"projects" : 
			[
				{
					"directoryIndexes" : 
					[
						0
					],
					"name" : "WordleSolver",
					"targetIndexes" : 
					[
						0,
						1,
						2
					]
				}
			],
			"targets" : 
			[
				{
					"directoryIndex" : 0,
					"id" : "ALL_BUILD::@6890427a1f51a3e7e1df",
					"jsonFile" : "target-ALL_BUILD-MinSizeRel-d00ad5da430fcfb9aa1d.json",
					"name" : "ALL_BUILD",
					"projectIndex" : 0
				},
				{
					"directoryIndex" : 0,
					"id" : "WordleSolver::@6890427a1f51a3e7e1df",
					"jsonFile" : "target-WordleSolver-MinSizeRel-d4bf2548d922acd04068.json",
					"name" : "WordleSolver",
					"projectIndex" : 0
				},
				{
					"directoryIndex" : 0,
					"id" : "ZERO_CHECK::@6890427a1f51a3e7e1df",
					"jsonFile" : "target-ZERO_CHECK-MinSizeRel-7467a3f982a3dc1f794d.json",
					"name" : "ZERO_CHECK",
					"projectIndex" : 0
				}
			]
		},
		{
			"abstractTargets" : [],
			"directories" : 
			[
				{
					"build" : ".",
					"jsonFile" : "directory-.-RelWithDebInfo-f6f22219c74102c3da70.json",
					"minimumCMakeVersion" : 
					{
						"string" : "3.15"
					},
					"projectIndex" : 0,
					"source" : ".",
					"targetIndexes" : 
					[
						0,
						1,
						2
					]
				}
			],
			"name" : "RelWithDebInfo",
			"projects" : 
			[
				{
					"directoryIndexes" : 
					[
						0
					],
					"name" : "WordleSolver",
					"targetIndexes" : 
					[
						0,
						1,
						2
					]
				}
			],
			"targets" : 
			[
				{
					"directoryIndex" : 0,
					"id" : "ALL_BUILD::@6890427a1f51a3e7e1df",
					"jsonFile" : "target-ALL_BUILD-RelWithDebInfo-d00ad5da430fcfb9aa1d.json",
					"name" : "ALL_BUILD",
					"projectIndex" : 0
				},
				{
					"directoryIndex" : 0,
					"id" : "WordleSolver::@6890427a1f51a3e7e1df",
					"jsonFile" : "target-WordleSolver-RelWithDebInfo-3b66d7feebbbc5d7d361.json",
					"name" : "WordleSolver",
					"projectIndex" : 0
				},
				{
					"directoryIndex" : 0,
					"id" : "ZERO_CHECK::@6890427a1f51a3e7e1df",
					"jsonFile" : "target-ZERO_CHECK-RelWithDebInfo-7467a3f982a3dc1f794d.json",
					"name" : "ZERO_CHECK",
					"projectIndex" : 0
				}
			]
		}
	],
	"kind" : "codemodel",
	"paths" : 
	{
		"build" : "C:/Users/trbec/Documents/WordleSolver/build",
		"source" : "C:/Users/trbec/Documents/WordleSolver"
	},
	"version" : 
	{
		"major" : 2,
		"minor" : 9
	}
}
